OTP/__init__.py
OTP/otp.py
OTP/version.py
robotframework_otp-1.0.0.dist-info/METADATA
robotframework_otp-1.0.0.dist-info/WHEEL
robotframework_otp-1.0.0.dist-info/top_level.txt
robotframework_otp-1.0.0.dist-info/RECORD
