Metadata-Version: 2.1
Name: robotframework-otp
Version: 1.0.0
Summary: Robot Framework OTP authenticator
Home-page: https://github.com/itsautomic/robotframework-otp
Author: Robot Framework Developers
Author-email: robotframework@gmail.com
License: Apache License 2.0
Keywords: robotframework testing testautomation otp totp
Platform: any
Classifier: Development Status :: 5 - Production/Stable
Classifier: License :: OSI Approved :: Apache Software License
Classifier: Operating System :: OS Independent
Classifier: Programming Language :: Python
Classifier: Programming Language :: Python :: 2.7
Classifier: Programming Language :: Python :: 3.8
Classifier: Topic :: Software Development :: Testing
Classifier: Framework :: Robot Framework
Classifier: Framework :: Robot Framework :: Library
Requires-Dist: robotframework (>=3.0)
